ps_data_science_tools/__init__.py
ps_data_science_tools/data/__init__.py
ps_data_science_tools/data/transforms.py
ps_data_science_tools/data/utils.py
ps_data_science_tools/data/visualization.py
ps_data_science_tools/metrics/__init__.py
ps_data_science_tools/metrics/classification.py
ps_data_science_tools/metrics/regression.py
ps_data_science_tools/models/__init__.py
ps_data_science_tools/models/evaluation.py
ps_data_science_tools/models/training.py
ps_data_science_tools/models/utils.py
ps_data_science_tools/utils/__init__.py
ps_data_science_tools/utils/helpers.py
ps_data_science_tools-0.2.0.dist-info/METADATA
ps_data_science_tools-0.2.0.dist-info/WHEEL
ps_data_science_tools-0.2.0.dist-info/top_level.txt
ps_data_science_tools-0.2.0.dist-info/RECORD
